LICENSE
MANIFEST.in
README.md
setup.py
assets/example.jpg
manga_abang/__init__.py
manga_abang/__main__.py
manga_abang/ocr.py
manga_abang/run.py
manga_abang.egg-info/PKG-INFO
manga_abang.egg-info/SOURCES.txt
manga_abang.egg-info/dependency_links.txt
manga_abang.egg-info/entry_points.txt
manga_abang.egg-info/requires.txt
manga_abang.egg-info/top_level.txt