Metadata-Version: 2.1
Name: manga-abang
Version: 0.1.3
Summary: OCR for Japanese manga
Home-page: https://github.com/AbangTanYiHan/manga_abang
License: Apache License 2.0
Classifier: Programming Language :: Python :: 3
License-File: LICENSE
